Metadata-Version: 2.1
Name: disortify
Version: 0.1.0
Summary: disortify python library for sorting,modifying and displaying data in various format.
Home-page: https://github.com/christian0311/disortify
Author: christian
Author-email: christiang03112003@gmail.com
License: MIT
Classifier: Programming Language :: Python :: 3
Classifier: License :: OSI Approved :: MIT License
Classifier: Operating System :: OS Independent
License-File: LICENSE
